ranged_heap/__init__.py
ranged_heap/bisectw.py
ranged_heap/errors.py
ranged_heap/py.typed
ranged_heap/ranged_heap.py
ranged_heap-0.1.0.dist-info/METADATA
ranged_heap-0.1.0.dist-info/WHEEL
ranged_heap-0.1.0.dist-info/RECORD
