Metadata-Version: 2.1
Name: ranged_heap
Version: 0.1.0
Summary: RangedHeap data structure
Home-page: https://github.com/giuseppeambrosio97/ranged-heap
License: Apache-2.0
Keywords: datastructure,heap,greedy-algorithm
Author: Giuseppe Ambrosio
Author-email: giuambro97@gmail.com
Maintainer: Giuseppe Ambrosio
Maintainer-email: giuambro97@gmail.com
Requires-Python: >=3.9,<4.0
Classifier: License :: OSI Approved :: Apache Software License
Classifier: Programming Language :: Python :: 3
Classifier: Programming Language :: Python :: 3.9
Classifier: Programming Language :: Python :: 3.10
Classifier: Programming Language :: Python :: 3.11
Classifier: Programming Language :: Python :: 3.12
Project-URL: Repository, https://github.com/giuseppeambrosio97/ranged-heap
